jstocks
