Metadata-Version: 2.4
Name: django-jstocks
Version: 0.5.4
Summary: Collection of small utilities for Django and Django REST framework projects.
Author-email: Jani Kajala <kajala@gmail.com>
License-Expression: MIT
Project-URL: Homepage, https://github.com/kajala/django-jstocks
Project-URL: Issues, https://github.com/kajala/django-jstocks/issues
Classifier: Programming Language :: Python :: 3
Classifier: Operating System :: OS Independent
Requires-Python: >=3.8
License-File: LICENSE.txt
Requires-Dist: Django>=3.1
Requires-Dist: django-jutil>=3.11.4
Requires-Dist: openpyxl>=3.0.5
Requires-Dist: django-cryptography-django5>=2.2
Dynamic: license-file
